inoutlogger/__init__.py
inoutlogger/decorators.py
inoutlogger/utils.py
inoutlogger-1.0.3.dist-info/LICENSE
inoutlogger-1.0.3.dist-info/METADATA
inoutlogger-1.0.3.dist-info/WHEEL
inoutlogger-1.0.3.dist-info/top_level.txt
inoutlogger-1.0.3.dist-info/RECORD
