Metadata-Version: 2.1
Name: inoutlogger
Version: 1.0.3
Summary: Decorator based utility to implement Entry-Exit logs for methods
Home-page: https://github.com/PanksSuthar/InOutLogger
Author: Pankaj Suthar
Author-email: sutharpanks.opensource@gmail.com
License: UNKNOWN
Platform: UNKNOWN
Classifier: Programming Language :: Python :: 3
Classifier: License :: OSI Approved :: MIT License
Classifier: Operating System :: OS Independent
Requires-Python: >=3.6
